fllog/__init__.py
fllog/_fllog.py
fllog/_version.py
fllog/modemap.py
fllog/wsjtx.py
fllog-0.1.5.dist-info/LICENSE
fllog-0.1.5.dist-info/METADATA
fllog-0.1.5.dist-info/WHEEL
fllog-0.1.5.dist-info/entry_points.txt
fllog-0.1.5.dist-info/top_level.txt
fllog-0.1.5.dist-info/RECORD
