Metadata-Version: 2.1
Name: fllog
Version: 0.1.5
Summary: Log contact made on fldigi to MacLoggerDX.
Author: Fred C. (W6BSD)
License: BSD 2-Clause License
Project-URL: Documentation, https://github.com/0x9900/fllog/
Project-URL: Source, https://github.com/0x9900/fllog
Project-URL: Tracker, https://github.com/0x9900/fllog/issues
Classifier: Intended Audience :: End Users/Desktop
Classifier: Intended Audience :: Telecommunications Industry
Classifier: License :: OSI Approved :: BSD License
Classifier: Operating System :: OS Independent
Classifier: Programming Language :: Python :: 3.10
Classifier: Programming Language :: Python :: 3.11
Classifier: Programming Language :: Python :: 3.12
Classifier: Programming Language :: Python
Classifier: Topic :: Communications :: Ham Radio
Requires-Python: >=3.10
License-File: LICENSE
Provides-Extra: dev
Requires-Dist: pre-commit; extra == "dev"
Requires-Dist: ipdb; extra == "dev"
Requires-Dist: flake8; extra == "dev"
Requires-Dist: mypy; extra == "dev"
Requires-Dist: isort; extra == "dev"
